racingbars/__init__.py
racingbars-0.0.0.dist-info/WHEEL
racingbars-0.0.0.dist-info/METADATA
racingbars-0.0.0.dist-info/RECORD
