Metadata-Version: 2.1
Name: racingbars
Version: 0.0.0
Summary: Bar chart race, easy to use, based on d3
License: MIT
Author: Hatem Hosny
Author-email: hatemhosny@gmail.com
Requires-Python: >=3.7,<4.0
Classifier: License :: OSI Approved :: MIT License
Classifier: Programming Language :: Python :: 3
Classifier: Programming Language :: Python :: 3.7
Classifier: Programming Language :: Python :: 3.8
